{"frames": {

"shore_1":
{
	"frame": {"x":438,"y":1010,"w":429,"h":248},
	"rotated": false,
	"trimmed": true,
	"spriteSourceSize": {"x":0,"y":0,"w":429,"h":248},
	"sourceSize": {"w":437,"h":254}
},
"shore_10":
{
	"frame": {"x":2,"y":2,"w":435,"h":252},
	"rotated": false,
	"trimmed": true,
	"spriteSourceSize": {"x":0,"y":0,"w":435,"h":252},
	"sourceSize": {"w":437,"h":254}
},
"shore_11":
{
	"frame": {"x":2,"y":256,"w":434,"h":251},
	"rotated": false,
	"trimmed": true,
	"spriteSourceSize": {"x":0,"y":0,"w":434,"h":251},
	"sourceSize": {"w":437,"h":254}
},
"shore_12":
{
	"frame": {"x":439,"y":2,"w":435,"h":251},
	"rotated": false,
	"trimmed": true,
	"spriteSourceSize": {"x":0,"y":1,"w":435,"h":251},
	"sourceSize": {"w":437,"h":254}
},
"shore_2":
{
	"frame": {"x":438,"y":1010,"w":429,"h":248},
	"rotated": false,
	"trimmed": true,
	"spriteSourceSize": {"x":0,"y":0,"w":429,"h":248},
	"sourceSize": {"w":437,"h":254}
},
"shore_3":
{
	"frame": {"x":438,"y":759,"w":432,"h":249},
	"rotated": false,
	"trimmed": true,
	"spriteSourceSize": {"x":0,"y":0,"w":432,"h":249},
	"sourceSize": {"w":437,"h":254}
},
"shore_4":
{
	"frame": {"x":438,"y":759,"w":432,"h":249},
	"rotated": false,
	"trimmed": true,
	"spriteSourceSize": {"x":0,"y":0,"w":432,"h":249},
	"sourceSize": {"w":437,"h":254}
},
"shore_5":
{
	"frame": {"x":439,"y":255,"w":434,"h":250},
	"rotated": false,
	"trimmed": true,
	"spriteSourceSize": {"x":0,"y":0,"w":434,"h":250},
	"sourceSize": {"w":437,"h":254}
},
"shore_6":
{
	"frame": {"x":439,"y":255,"w":434,"h":250},
	"rotated": false,
	"trimmed": true,
	"spriteSourceSize": {"x":0,"y":0,"w":434,"h":250},
	"sourceSize": {"w":437,"h":254}
},
"shore_7":
{
	"frame": {"x":438,"y":507,"w":434,"h":250},
	"rotated": false,
	"trimmed": true,
	"spriteSourceSize": {"x":0,"y":0,"w":434,"h":250},
	"sourceSize": {"w":437,"h":254}
},
"shore_8":
{
	"frame": {"x":2,"y":509,"w":434,"h":251},
	"rotated": false,
	"trimmed": true,
	"spriteSourceSize": {"x":0,"y":0,"w":434,"h":251},
	"sourceSize": {"w":437,"h":254}
},
"shore_9":
{
	"frame": {"x":2,"y":762,"w":434,"h":251},
	"rotated": false,
	"trimmed": true,
	"spriteSourceSize": {"x":0,"y":0,"w":434,"h":251},
	"sourceSize": {"w":437,"h":254}
}},
"meta": {
	"app": "http://www.codeandweb.com/texturepacker",
	"version": "1.0",
	"image": "shoreline.png",
	"format": "RGBA8888",
	"size": {"w":876,"h":1261},
	"scale": "1",
	"smartupdate": "$TexturePacker:SmartUpdate:057a0c9cdc3205ed009ee985f38637b7:683a839e18469ef956ce935e2c28256d:0c64744b78d497d7a6bb09fbdb1033d7$"
}
}
