{
"images": ["wadSS.png"],
"frames": [

    [1588, 214, 120, 104],
    [1588, 108, 120, 104],
    [1466, 214, 120, 104],
    [1466, 108, 120, 104],
    [1588, 2, 120, 104],
    [1466, 2, 120, 104],
    [1344, 214, 120, 104],
    [1344, 108, 120, 104],
    [1344, 2, 120, 104],
    [1222, 214, 120, 104],
    [1222, 108, 120, 104],
    [1222, 2, 120, 104],
    [1100, 214, 120, 104],
    [1100, 108, 120, 104],
    [1100, 2, 120, 104],
    [978, 214, 120, 104],
    [978, 108, 120, 104],
    [978, 2, 120, 104],
    [856, 214, 120, 104],
    [856, 108, 120, 104],
    [856, 2, 120, 104],
    [734, 214, 120, 104],
    [734, 108, 120, 104],
    [734, 2, 120, 104],
    [612, 214, 120, 104],
    [612, 108, 120, 104],
    [612, 2, 120, 104],
    [490, 214, 120, 104],
    [490, 108, 120, 104],
    [490, 2, 120, 104],
    [368, 214, 120, 104],
    [368, 108, 120, 104],
    [368, 2, 120, 104],
    [246, 214, 120, 104],
    [246, 108, 120, 104],
    [246, 2, 120, 104],
    [124, 214, 120, 104],
    [124, 108, 120, 104],
    [124, 2, 120, 104],
    [2, 214, 120, 104],
    [2, 108, 120, 104],
    [2, 2, 120, 104]
],
"animations": {

        "Cash Bundle 120x104_00000":[0],
        "Cash Bundle 120x104_00001":[1],
        "Cash Bundle 120x104_00002":[2],
        "Cash Bundle 120x104_00003":[3],
        "Cash Bundle 120x104_00004":[4],
        "Cash Bundle 120x104_00005":[5],
        "Cash Bundle 120x104_00006":[6],
        "Cash Bundle 120x104_00007":[7],
        "Cash Bundle 120x104_00008":[8],
        "Cash Bundle 120x104_00009":[9],
        "Cash Bundle 120x104_00010":[10],
        "Cash Bundle 120x104_00011":[11],
        "Cash Bundle 120x104_00012":[12],
        "Cash Bundle 120x104_00013":[13],
        "Cash Bundle 120x104_00014":[14],
        "Cash Bundle 120x104_00015":[15],
        "Cash Bundle 120x104_00016":[16],
        "Cash Bundle 120x104_00017":[17],
        "Cash Bundle 120x104_00018":[18],
        "Cash Bundle 120x104_00019":[19],
        "Cash Bundle 120x104_00020":[20],
        "Cash Bundle 120x104_00021":[21],
        "Cash Bundle 120x104_00022":[22],
        "Cash Bundle 120x104_00023":[23],
        "Cash Bundle 120x104_00024":[24],
        "Cash Bundle 120x104_00025":[25],
        "Cash Bundle 120x104_00026":[26],
        "Cash Bundle 120x104_00027":[27],
        "Cash Bundle 120x104_00028":[28],
        "Cash Bundle 120x104_00029":[29],
        "Cash Bundle 120x104_00030":[30],
        "Cash Bundle 120x104_00031":[31],
        "Cash Bundle 120x104_00032":[32],
        "Cash Bundle 120x104_00033":[33],
        "Cash Bundle 120x104_00034":[34],
        "Cash Bundle 120x104_00035":[35],
        "Cash Bundle 120x104_00036":[36],
        "Cash Bundle 120x104_00037":[37],
        "Cash Bundle 120x104_00038":[38],
        "Cash Bundle 120x104_00039":[39],
        "Cash Bundle 120x104_00040":[40],
        "Cash Bundle Shadow 120x104_00000":[41]
},
"texturepacker": [
        "SmartUpdateHash: $TexturePacker:SmartUpdate:a5b9541b263f7a7b3fbd23eab78d85e8:8dc4ca87fc48d1b8ffe25ce6d51b6043:8f0c8adda39e7b361c24493282085d5b$",
        "Created with TexturePacker (http://www.texturepacker.com) for EaselJS"
]
}
