{"frames": [

{
	"filename": "cowboyShotRight_1",
	"frame": {"x":664,"y":2,"w":338,"h":423},
	"rotated": false,
	"trimmed": true,
	"spriteSourceSize": {"x":1,"y":63,"w":338,"h":423},
	"sourceSize": {"w":340,"h":489}
},
{
	"filename": "cowboyShotRight_2",
	"frame": {"x":324,"y":2,"w":338,"h":434},
	"rotated": false,
	"trimmed": true,
	"spriteSourceSize": {"x":1,"y":52,"w":338,"h":434},
	"sourceSize": {"w":340,"h":489}
},
{
	"filename": "cowboyShotRight_3",
	"frame": {"x":324,"y":438,"w":334,"h":450},
	"rotated": false,
	"trimmed": true,
	"spriteSourceSize": {"x":4,"y":35,"w":334,"h":450},
	"sourceSize": {"w":340,"h":489}
},
{
	"filename": "cowboyShotRight_4",
	"frame": {"x":664,"y":427,"w":327,"h":468},
	"rotated": false,
	"trimmed": true,
	"spriteSourceSize": {"x":9,"y":16,"w":327,"h":468},
	"sourceSize": {"w":340,"h":489}
},
{
	"filename": "cowboyShotRight_5",
	"frame": {"x":2,"y":2,"w":320,"h":482},
	"rotated": false,
	"trimmed": true,
	"spriteSourceSize": {"x":15,"y":1,"w":320,"h":482},
	"sourceSize": {"w":340,"h":489}
},
{
	"filename": "cowboyShotRight_6",
	"frame": {"x":2,"y":486,"w":295,"h":384},
	"rotated": false,
	"trimmed": true,
	"spriteSourceSize": {"x":23,"y":97,"w":295,"h":384},
	"sourceSize": {"w":340,"h":489}
}],
"meta": {
	"app": "http://www.codeandweb.com/texturepacker",
	"version": "1.0",
	"image": "cowboyShotRightAnimation.png",
	"format": "RGBA8888",
	"size": {"w":1004,"h":897},
	"scale": "1",
	"smartupdate": "$TexturePacker:SmartUpdate:2da6e1822140a984852228a749c7cec9:d2e848ec6ba9566b43151f1dbe1a9f00:e05e1abd4857f436e27c93a48bd73fa1$"
}
}
